MANIFEST.in
README.rst
setup.py
django_richcontentblocks.egg-info/PKG-INFO
django_richcontentblocks.egg-info/SOURCES.txt
django_richcontentblocks.egg-info/dependency_links.txt
django_richcontentblocks.egg-info/requires.txt
django_richcontentblocks.egg-info/top_level.txt
richcontentblocks/__init__.py
richcontentblocks/admin.py
richcontentblocks/apps.py
richcontentblocks/models.py
richcontentblocks/tests.py
richcontentblocks/views.py
richcontentblocks/templatetags/__init__.py
richcontentblocks/templatetags/__init__.pyc
richcontentblocks/templatetags/rich_content_block.pyc
richcontentblocks/templatetags/rich_content_block_tags.py
richcontentblocks/templatetags/rich_content_block_tags.pyc