Metadata-Version: 1.1
Name: django-richcontentblocks
Version: 0.4.4
Summary: Simple (rich) content blocks for use on front end templates. With admin tool.
Home-page: https://github.com/django-emerge/django-richcontentblocks
Author: Django Radonich-Camp
Author-email: django@emergeinteractive.com
License: MIT License
Download-URL: https://github.com/django-emerge/django-richcontentblocks/tarball/0.4.4
Platform: UNKNOWN
Classifier: Environment :: Web Environment
Classifier: Framework :: Django
Classifier: Intended Audience :: Developers
Classifier: License :: OSI Approved :: MIT License
Classifier: Operating System :: OS Independent
Classifier: Programming Language :: Python
Classifier: Topic :: Internet :: WWW/HTTP :: Dynamic Content
